{
  "$schema": "http://json-schema.org/draft-07/schema#",
  "type": "object",
  "properties": {
    "ballerina": {
      "type": "object",
      "properties": {
        "log": {
          "type": "object",
          "properties": {
            "destinations": {
              "type": "array",
              "items": {
                "anyOf": [
                  {
                    "type": "object",
                    "properties": {
                      "type": {
                        "enum": [
                          "stderr",
                          "stdout"
                        ]
                      }
                    },
                    "additionalProperties": false,
                    "required": [
                      "type"
                    ],
                    "name": "ballerina/log:2.14.0:StandardDestination"
                  },
                  {
                    "type": "object",
                    "properties": {
                      "type": {
                        "enum": [
                          "file"
                        ]
                      },
                      "path": {
                        "type": "string"
                      },
                      "mode": {
                        "enum": [
                          "APPEND",
                          "TRUNCATE"
                        ]
                      }
                    },
                    "additionalProperties": false,
                    "required": [
                      "type",
                      "path",
                      "mode"
                    ],
                    "name": "ballerina/log:2.14.0:FileOutputDestination"
                  }
                ]
              },
              "description": ""
            },
            "modules": {
              "type": "array",
              "items": {
                "type": "object",
                "properties": {
                  "name": {
                    "type": "string"
                  },
                  "level": {
                    "enum": [
                      "WARN",
                      "INFO",
                      "ERROR",
                      "DEBUG"
                    ]
                  }
                },
                "additionalProperties": false,
                "required": [
                  "name",
                  "level"
                ],
                "name": "ballerina/log:2.14.0:Module"
              },
              "description": ""
            },
            "keyValues": {
              "type": "object",
              "properties": {
                "msg": {},
                "error": {},
                "stackTrace": {},
                "module": {}
              },
              "additionalProperties": false,
              "name": "ballerina/log:2.14.0:AnydataKeyValues",
              "description": ""
            },
            "format": {
              "enum": [
                "logfmt",
                "json"
              ],
              "description": ""
            },
            "level": {
              "enum": [
                "WARN",
                "INFO",
                "ERROR",
                "DEBUG"
              ],
              "description": ""
            },
            "enableSensitiveDataMasking": {
              "type": "boolean",
              "description": ""
            }
          },
          "additionalProperties": false
        }
      },
      "additionalProperties": false
    },
    "wso2": {
      "type": "object",
      "properties": {
        "new_shopify_customer_to_stripe": {
          "type": "object",
          "properties": {
            "shopifyConfig": {
              "type": "object",
              "properties": {
                "apiSecretKey": {
                  "type": "string"
                }
              },
              "additionalProperties": false,
              "required": [
                "apiSecretKey"
              ],
              "description": ""
            },
            "stripeConfig": {
              "type": "object",
              "properties": {
                "secretKey": {
                  "type": "string"
                }
              },
              "additionalProperties": false,
              "required": [
                "secretKey"
              ],
              "description": ""
            }
          },
          "additionalProperties": false,
          "required": [
            "shopifyConfig",
            "stripeConfig"
          ]
        }
      },
      "additionalProperties": false
    }
  },
  "additionalProperties": false
}
